{
  "perc_income_min_price_25": {
    "category": "Broadband",
    "measure_table": "dcmdva_broadbandnow_acs_sdad_2021_perc_income_on_internet",
    "full_name": "perc_income_on_internet:perc_income_min_price_25",
    "type": "percent",
    "short_name": "Percentage of income for good internet",
    "long_name": "The minimum price for good internet (25 MB/s upload) as a percentage of median household income",
    "short_description": "The minimum price for good internet (25 MB/s upload) as a percentage of median household income",
    "long_description": "The minimum price for good internet (25 MB/s upload) as a percentage of median household income.",
    "statement": "Good internet costs {value} of the median household income in {features.name}.",
    "equity_category": "Affordability",
    "sources": [
      {
        "name": "American Community Survey",
        "date_accessed": 2021,
        "url": "https://www.census.gov/programs-surveys/acs.html"
      },
      {
        "name": "Broadband Now",
        "date_accessed": 2021,
        "url": "https://broadbandnow.com/"
      }
    ]
  }
}
